odoo/addons/website_sale_cart_selectable/README.rst
odoo/addons/website_sale_cart_selectable/__init__.py
odoo/addons/website_sale_cart_selectable/__manifest__.py
odoo/addons/website_sale_cart_selectable/i18n/ca.po
odoo/addons/website_sale_cart_selectable/i18n/es.po
odoo/addons/website_sale_cart_selectable/i18n/fr.po
odoo/addons/website_sale_cart_selectable/i18n/website_sale_cart_selectable.pot
odoo/addons/website_sale_cart_selectable/models/__init__.py
odoo/addons/website_sale_cart_selectable/models/product.py
odoo/addons/website_sale_cart_selectable/readme/CONTRIBUTORS.rst
odoo/addons/website_sale_cart_selectable/readme/DESCRIPTION.rst
odoo/addons/website_sale_cart_selectable/readme/USAGE.rst
odoo/addons/website_sale_cart_selectable/static/description/icon.png
odoo/addons/website_sale_cart_selectable/static/description/index.html
odoo/addons/website_sale_cart_selectable/views/product_view.xml
odoo/addons/website_sale_cart_selectable/views/website_sale_template.xml
odoo12_addon_website_sale_cart_selectable-12.0.1.0.0.99.dev12.dist-info/METADATA
odoo12_addon_website_sale_cart_selectable-12.0.1.0.0.99.dev12.dist-info/WHEEL
odoo12_addon_website_sale_cart_selectable-12.0.1.0.0.99.dev12.dist-info/top_level.txt
odoo12_addon_website_sale_cart_selectable-12.0.1.0.0.99.dev12.dist-info/RECORD
